[
  {
    "sentence": "765 프로의 미래는, 이곳에 있어…!",
    "author": "아이돌 마스터 밀리언 라이브!"
  },
  {
    "sentence": "Princess Be Ambitious!!",
    "author": "PRINCESS STARS - Princess Be Ambitious!!"
  },
  {
    "sentence": "울려라 우리들의 목소리 스테이지부터 뛰쳐 날아가",
    "author": "레전드 데이즈 - 암호는 스타트 업!"
  },
  {
    "sentence": "We are LEGEND DAYS! Looking for MILLION STARS!",
    "author": "레전드 데이즈 - 암호는 스타트 업!"
  },
  {
    "sentence": "손수 만든 '무도관' 간판은 무지개 빛",
    "author": "아이돌 마스터 밀리언 라이브! - Thank You!"
  },
  {
    "sentence": "Thank you for…",
    "author": "아이돌 마스터 밀리언 라이브! - Thank You!"
  },
  {
    "sentence": "ToP!!!!!!!!!!!!! 제일로 반짝여라!",
    "author": "765AS - ToP!!!!!!!!!!!!!"
  },
  {
    "sentence": "프로듀서 씨! 돔이에요, 돔!",
    "author": "아마미 하루카 - 아이돌 마스터"
  },
  {
    "sentence": "연기에 휩싸이는 과일",
    "author": "류규코마치 - SMOKY FRUITS"
  },
  {
    "sentence": "신SUMMER!! 모두들!! HAPPY하게 되자",
    "author": "765AS - 神SUMMER!!"
  },
  {
    "sentence": "The world is all one !!",
    "author": "765AS - The world is all one !!"
  },
  {
    "sentence": "널 빠져들게 하고 싶어서 초조해하는 날 사랑해줘",
    "author": "미나세 이오리 - カプチーノ"
  },
  {
    "sentence": "정말 좋아해 몇 번이든 말해줘",
    "author": "765AS - アマテラス"
  },
  {
    "sentence": "Yeah! 신나는 휴일!",
    "author": "후타미 마미 - Yeah! めっちゃホリディ"
  },
  {
    "sentence": "기타 솔로 컴온!",
    "author": "타카츠키 야요이 - キラメキラリ"
  },
  {
    "sentence": "반짝이는 스테이지에 서면 최고의 기분을 맛볼 수 있어",
    "author": "765AS - 自分REST@RT"
  },
  {
    "sentence": "형태를 바꿔가는 삼각형 감정마저 굴러가기 시작해 (롤러코스터!?)",
    "author": "스오 모모코 - ローリング△さんかく"
  },
  {
    "sentence": "1 곱하기 5는 MILLION!",
    "author": "스오 모모코 - MY STYLE! OUR STYLE!!!!"
  },
  {
    "sentence": "세계에서 마음을 전할 수 있다면 내일은 분명 빛나는 미러볼",
    "author": "미나세 이오리 - 地球ミラーボウル"
  },
  {
    "sentence": "하나씩 하나씩 날아가라!",
    "author": "가나하 히비키 - smiley days"
  },
  {
    "sentence": "최고? 감동?",
    "author": "후타미 아미, 후타미 마미 - 黎明スターライン"
  },
  {
    "sentence": "움바바 움하하!",
    "author": "오오가미 타마키, 후타미 마미 - ジャングル☆パーティー"
  },
  {
    "sentence": "미나세 이오리, 15살이에요",
    "author": "미나세 이오리 - 아이돌 마스터"
  },
  {
    "sentence": "후타미 아미, 후타미 마미! 트윈즈!",
    "author": "후타미 아미, 후타미 아미 - 아이돌 마스터"
  },
  {
    "sentence": "바로 불러낼 수 있는게 너밖에 없었을 뿐이야! 더 노력해. 그럼 또 불러줄 테니까…",
    "author": "미나세 이오리 - 아이돌 마스터"
  },
  {
    "sentence": "어째서 당신이 리더인거죠?",
    "author": "키자타와 시호 - 아이돌 마스터 무비: 빛의 저편으로!"
  },
  {
    "sentence": "큿",
    "author": "키사라기 치하야 - 아이돌 마스터"
  },
  {
    "sentence": "잡았다 게로!",
    "author": "키사라기 치하야 - 게로게로 치킨"
  },
  {
    "sentence": "앞이 전혀 안보여... 진짜 이길 맞아?",
    "author": "가나하 히비키"
  },
  {
    "sentence": "가지마, 타카네! 이 과자 다 줄게!",
    "author": "가나하 히비키"
  },
  {
    "sentence": "허니!",
    "author": "호시이 미키 - 아이돌 마스터"
  },
  {
    "sentence": "마빡아!",
    "author": "호시이 미키 - 아이돌 마스터"
  },
  {
    "sentence": "쿠후후... 이제부터 잔뜩 놀자구, 두목!",
    "author": "오오가미 타마키 - 아이돌 마스터 밀리언 라이브!"
  },
  {
    "sentence": "나는 나가요시 스바루. 아이돌이 된다는 것이 뭔지 아직 잘 모르겠지만, 어쨌든 열심히 할게! 잘 부탁해!",
    "author": "나가요시 스바루 - 아이돌 마스터 밀리언 라이브!"
  },
  {
    "sentence": "이 세계에선 모모코가 선배니까, 말 잘 들어야 한다구?",
    "author": "스오 모모코 - 아이돌 마스터 밀리언 라이브!"
  },
  {
    "sentence": "와-! 이렇게 대단한 프로듀서씨가 있다면, 마츠리의 미래는 원더호-! 인거예요!",
    "author": "토쿠가와 마츠리 - 아이돌 마스터 밀리언 라이브!"
  },
  {
    "sentence": "호? 공주는 마시멜로 좋아하는거예요.",
    "author": "토쿠가와 마츠리 - 아이돌 마스터 밀리언 라이브!"
  },
  {
    "sentence": "난 어덜트 섹시 레이디라구!",
    "author": "바바 코노미 - 아이돌 마스터 밀리언 라이브!"
  },
  {
    "sentence": "안나... 안나와...?",
    "author": "모치즈키 안나 - 아이돌 마스터 밀리언 라이브!"
  },
  {
    "sentence": "<시어터 안에서 야구 금지>",
    "author": "타나카 코토하 - 아이돌 마스터 밀리언 라이브!"
  },
  {
    "sentence": "짜안! 주목! 아카네쨩 등!장! 잘 부탁해! 프로쨩!",
    "author": "노노하라 아카네 - 아이돌 마스터 밀리언 라이브!"
  },
  {
    "sentence": "아카네쨩의 푸딩이 없어! 소중하게 넣어놨는데도! 범인은 아카네쨩 인형의 재료로 넣어주겠어! 프로ㅃ쨩도 도와줘!",
    "author": "노노하라 아카네 - 아이돌 마스터 밀리언 라이브!"
  },
  {
    "sentence": "시, 싫어! 나는 일하지 않을거야!",
    "author": "후타바 안즈"
  },
  {
    "sentence": "학교의 허가? 인정할 수 없어!",
    "author": "호시조라 린 - 러브라이브!"
  },
  {
    "sentence": "이루어져라, 우리들의 꿈!",
    "author": "러브라이브!"
  },
  {
    "sentence": "난 거북이야, 병신아.",
    "author": "아쿠아 맨이 말을 건 바다거북"
  },
  {
    "sentence": "모든 렌턴들은 반지를 착용했으며 그 중엔 반지를 닦아주는 이도 있었다.",
    "author": "그린 렌턴: 반지의 선택"
  },
  {
    "sentence": "아니다 이 악마야",
    "author": "그린 렌턴: 반지의 선택"
  },
  {
    "sentence": "할… 날 따뜻하게 해주렴",
    "author": "그린 렌턴: 반지의 선택"
  },
  {
    "sentence": "팝콘이나 가져와라 로빈.",
    "author": "배트맨"
  },
  {
    "sentence": "내가 고자라니",
    "author": "심영 - 야인시대"
  },
  {
    "sentence": "누가 기침 소리를 내었는가",
    "author": "궁예 - 태조 왕건"
  },
  {
    "sentence": "I am Groot.",
    "author": "그루트"
  },
  {
    "sentence": "엄마...",
    "author": "효자 닉 퓨리 - 어벤져스: 인피니티 워"
  },
  {
    "sentence": "안녕하세요!!! 태보는 지금 전세계적으로 인기를 끌고 있는데요,",
    "author": "조혜련 - 태보 다이어트"
  },
  {
    "sentence": "절 대 태 보 해 @==(^0^)==@",
    "author": "조혜련과 태보의 저주"
  },
  {
    "sentence": "난 사이코패스가 아니야 앤더슨. 고기능 소시오패스지. 검색 좀 해.",
    "author": "셜록 홈즈 - 셜록"
  },
  {
    "sentence": "바티칸 카메오!",
    "author": "셜록 홈즈 - 셜록"
  },
  {
    "sentence": "Elementary, My Dear Watson!",
    "author": "셜록 홈즈 - 셜록, 엘리멘트리"
  },
  {
    "sentence": "Miss me?",
    "author": "존 모리어티 - 셜록"
  },
  {
    "sentence": "내 목숨을 아이어에.",
    "author": "프로토스 - 스타크래프트 시리즈"
  },
  {
    "sentence": "The cake is a lie!",
    "author": "더그 랫맨 - 포탈"
  },
  {
    "sentence": "You're my hero",
    "author": "바넬로피 본 슈위츠 - 주먹왕 랄프"
  },
  {
    "sentence": "자비로운 공주로서 명하노라. 나에게 못되게 군 것들은 모두 처형이야",
    "author": "바넬로피 본 슈위츠 - 주먹왕 랄프"
  },
  {
    "sentence": "소고기는 자유 소프트웨어가 아닙니다",
    "author": "연합 우주의 어느 행성"
  },
  {
    "sentence": "판사님 이 명언은 고양이가 쳤습니다",
    "author": "포메라니안"
  },
  {
    "sentence": "지나가던 17살 여고생인데요 사이트 진심 후지네요 ㅋㅋ 진짜 레아아웃 보자마자 껐어요 두딸을 키우는 애아빠로서 이런 사이트 보여주기도 아깝네요",
    "author": "17살 애아빠 여고생"
  },
  {
    "sentence": "어딜 보시는 겁니까? 그건 제 잔상입니다.",
    "author": "잔상권"
  },
  {
    "sentence": "안녕하신가! 힘 세고 강한 아침, 만일 내게 물어보면 나는 왈도.",
    "author": "덫 사냥꾼 왈도 - 마이트 앤 매직"
  },
  {
    "sentence": "아희 아희 아희! 아희 아희 아희! 아희 아희 아희!",
    "author": "Ylvis - The Fox"
  },
  {
    "sentence": "아옳옳옳? 아옳옳옳옳!",
    "author": "머키 - 히어로즈 오브 더 스톰"
  },
  {
    "sentence": "가, 짐. 어서...",
    "author": "사라 케리건 - 스타크래프트 2"
  },
  {
    "sentence": "난 죽음을 경험한 적이 없네.",
    "author": "태사다르 - 스타크래프트 2"
  },
  {
    "sentence": "사실 지구는 평평합니다. 마인크래프트만 해도 알 수 있는 사실 아닌가요?",
    "author": "지구평평교"
  },
  {
    "sentence": "AHHHHHH",
    "author": "지미 반즈 - Big Enough"
  },
  {
    "sentence": "AAA? A AAAA. AAA, AAAAAA. AAAAA!",
    "author": "AAAAA AAAA - AAA"
  },
  {
    "sentence": "수학하는 놈들... 저리 꺼져라, 꺼져!",
    "author": "데커드 케인 - 디아블로 3"
  },
  {
    "sentence": "오랜만에 집에서 바나나 먹었다",
    "author": "브리트니 스피어스 - Lucky"
  },
  {
    "sentence": "뱅드림! 제노그라시아",
    "author": "우리 장르만 당할 수 없지"
  },
  {
    "sentence": "당신의 사이트 404로 대체되었다",
    "author": "앨런 다비리"
  },
  {
    "sentence": "항상 감사하십시오 and I also 시공 조아.",
    "author": "앨런 다비리"
  },
  {
    "sentence": "I can make you hands clap. 전국, 노래자랑!",
    "author": "J.E.B - 전국 Handclap 자랑"
  },
  {
    "sentence": "[여기에 텍스트 입력]",
    "author": "J.E.B"
  },
  {
    "sentence": "목사님 타시던 에쿠스 오늘은 장로님 타신다",
    "author": "J.E.B - 장로님 에쿠스 타신다"
  },
  {
    "sentence": "김치에 싸서 드셔보세요",
    "author": "무엇을?"
  },
  {
    "sentence": "태양 만세!",
    "author": "다크 소울"
  }
]